{"stat.chestOpened":19,"stat.walkOneCm":73377,"stat.drop.minecraft.item_frame":1,"stat.leaveGame":3,"stat.furnaceInteraction":1,"stat.jump":777,"stat.swimOneCm":3908,"stat.fallOneCm":11276,"stat.climbOneCm":12580,"stat.drop.minecraft.feather":16,"stat.crouchOneCm":83,"stat.useItem.minecraft.written_book":3,"stat.sprintOneCm":76740,"achievement.exploreAllBiomes":{"value":0,"progress":["Beach","Jungle","Forest","River","Plains","Desert","Taiga","Ice Mountains"]},"stat.craftItem.minecraft.stick":4,"stat.craftingTableInteraction":2,"achievement.openInventory":12,"stat.useItem.minecraft.snowball":4,"stat.damageTaken":750,"stat.pickup.minecraft.feather":16,"stat.pickup.minecraft.written_book":1,"stat.mobKills":1,"stat.craftItem.minecraft.bow":1,"stat.drop.minecraft.written_book":1,"stat.flyOneCm":159064,"stat.drop":18,"stat.playOneMinute":40771,"stat.killEntity.Sheep":1,"stat.sneakTime":68,"stat.pickup.minecraft.wool":1,"stat.damageDealt":91,"stat.pickup.minecraft.item_frame":2,"stat.timeSinceDeath":40771,"stat.pickup.minecraft.snowball":5,"stat.useItem.minecraft.wooden_axe":5,"stat.pickup.minecraft.minecart":5,"stat.pickup.minecraft.mutton":1}