{"stat.chestOpened":88,"stat.drop.minecraft.waterlily":3,"stat.pickup.minecraft.record_strad":1,"stat.recordPlayed":1,"stat.horseOneCm":54928,"stat.leaveGame":2,"stat.pickup.minecraft.waterlily":6,"stat.pickup.minecraft.stone_pickaxe":1,"stat.pickup.minecraft.record_stal":1,"stat.pickup.minecraft.dark_oak_boat":4,"stat.swimOneCm":15188,"stat.jump":7495,"stat.climbOneCm":16445,"stat.fallOneCm":233816,"stat.useItem.minecraft.dark_oak_boat":5,"stat.crouchOneCm":3074,"stat.pickup.minecraft.golden_helmet":1,"achievement.exploreAllBiomes":{"value":0,"progress":["Beach","Jungle","Forest","Ocean","River","Plains","Desert","Taiga","Extreme Hills","Extreme Hills Edge","Ice Mountains"]},"stat.craftingTableInteraction":1,"stat.boatOneCm":40871,"stat.useItem.minecraft.egg":2,"stat.damageTaken":10327,"stat.pickup.minecraft.feather":1,"stat.pickup.minecraft.written_book":1,"stat.dispenserInspected":1,"stat.noteblockTuned":80,"stat.flyOneCm":1629514,"stat.pickup.minecraft.glass_bottle":3,"stat.useItem.minecraft.record_strad":1,"stat.pickup.minecraft.lead":1,"stat.damageDealt":231,"stat.timeSinceDeath":27724,"stat.walkOneCm":322836,"stat.trappedChestTriggered":8,"stat.furnaceInteraction":3,"stat.pickup.minecraft.redstone_lamp":1,"stat.drop.minecraft.wool":2,"stat.drop.minecraft.redstone_lamp":1,"stat.useItem.minecraft.written_book":4,"stat.sprintOneCm":721329,"achievement.openInventory":8,"stat.mobKills":2,"stat.drop.minecraft.lava_bucket":2,"stat.pickup.minecraft.sugar":1,"stat.deaths":10,"stat.drop":8,"stat.pickup.minecraft.egg":2,"stat.playOneMinute":216443,"stat.killEntity.Sheep":1,"stat.sneakTime":1341,"stat.pickup.minecraft.wool":2,"stat.diveOneCm":28618}